geode_youwol/__init__.py
geode_youwol/youwol.py
geode_youwol/lib64/geode_youwol_py_youwol.cpython-312-x86_64-linux-gnu.so
geode_youwol/lib64/libGeode-YOUWOL_youwol.so
Geode_YOUWOL-1.0.3.dist-info/METADATA
Geode_YOUWOL-1.0.3.dist-info/WHEEL
Geode_YOUWOL-1.0.3.dist-info/top_level.txt
Geode_YOUWOL-1.0.3.dist-info/RECORD
