Metadata-Version: 2.1
Name: Geode-YOUWOL
Version: 1.0.3
Summary: Open source framework for representing and manipulating geometric models
Author-email: Geode-solutions <contact@geode-solutions.com>
License: MIT
Requires-Python: <3.13,>=3.9
Requires-Dist: opengeode-core ==15.1.2
Requires-Dist: opengeode-inspector ==6.0.0
